pyalluvial/__init__.py
pyalluvial/alluvial.py
pyalluvial-0.0.0.dist-info/LICENSE
pyalluvial-0.0.0.dist-info/METADATA
pyalluvial-0.0.0.dist-info/WHEEL
pyalluvial-0.0.0.dist-info/top_level.txt
pyalluvial-0.0.0.dist-info/RECORD
